odoo/addons/stock_packaging/README.rst
odoo/addons/stock_packaging/__init__.py
odoo/addons/stock_packaging/__manifest__.py
odoo/addons/stock_packaging/i18n/stock_packaging.pot
odoo/addons/stock_packaging/i18n/zh_CN.po
odoo/addons/stock_packaging/models/__init__.py
odoo/addons/stock_packaging/models/stock_move.py
odoo/addons/stock_packaging/models/stock_rule.py
odoo/addons/stock_packaging/readme/CONTRIBUTORS.rst
odoo/addons/stock_packaging/readme/DESCRIPTION.rst
odoo/addons/stock_packaging/readme/HISTORY.rst
odoo/addons/stock_packaging/readme/USAGE.rst
odoo/addons/stock_packaging/static/description/icon.png
odoo/addons/stock_packaging/static/description/index.html
odoo/addons/stock_packaging/tests/__init__.py
odoo/addons/stock_packaging/tests/test_stock_packaging.py
odoo/addons/stock_packaging/views/stock_rule.xml
odoo12_addon_stock_packaging-12.0.1.0.1.dist-info/METADATA
odoo12_addon_stock_packaging-12.0.1.0.1.dist-info/WHEEL
odoo12_addon_stock_packaging-12.0.1.0.1.dist-info/top_level.txt
odoo12_addon_stock_packaging-12.0.1.0.1.dist-info/RECORD
